{
  "ID": "6c6393fc-8ff0-4284-9b5e-e529b49aea06",
  "Version": "2.3.2.0",
  "Name": "StartScene",
  "Content": {
    "Content": {
      "Animation": {
        "Duration": 0,
        "Speed": 1.0,
        "Timelines": [],
        "ctype": "TimelineActionData"
      },
      "AnimationList": [],
      "ObjectData": {
        "Tag": 11,
        "Children": [
          {
            "FontSize": 14,
            "ButtonText": "",
            "TextColor": {
              "R": 65,
              "G": 65,
              "B": 70
            },
            "DisabledFileData": {
              "Type": "Default",
              "Path": "Default/Button_Disable.png",
              "Plist": ""
            },
            "PressedFileData": {
              "Type": "Normal",
              "Path": "StartScene/NewButton.png",
              "Plist": ""
            },
            "NormalFileData": {
              "Type": "Normal",
              "Path": "StartScene/NewButton.png",
              "Plist": ""
            },
            "Scale9Enable": true,
            "Scale9OriginX": 15,
            "Scale9OriginY": 11,
            "Scale9Width": 216,
            "Scale9Height": 53,
            "OutlineColor": {
              "G": 0,
              "B": 0
            },
            "ShadowColor": {
              "R": 110,
              "G": 110,
              "B": 110
            },
            "ShadowOffsetX": 2.0,
            "ShadowOffsetY": -2.0,
            "TouchEnable": true,
            "AnchorPoint": {
              "ScaleX": 0.5,
              "ScaleY": 0.5
            },
            "Position": {
              "X": 475.968,
              "Y": 307.968
            },
            "Scale": {
              "ScaleX": 1.0,
              "ScaleY": 1.0
            },
            "CColor": {},
            "IconVisible": false,
            "PrePosition": {
              "X": 0.4958,
              "Y": 0.4812
            },
            "PreSize": {
              "X": 0.2562,
              "Y": 0.1172
            },
            "LeftMargin": 352.968,
            "RightMargin": 361.032,
            "TopMargin": 294.532,
            "BottomMargin": 270.468,
            "CallBackType": "Touch",
            "CallBackName": "onTouchEvent",
            "Tag": 11,
            "ActionTag": 897915548,
            "Size": {
              "X": 246.0,
              "Y": 75.0
            },
            "Name": "NewGameButton",
            "ctype": "ButtonObjectData"
          }
        ],
        "Size": {
          "X": 960.0,
          "Y": 640.0
        },
        "Name": "StartScene",
        "ctype": "SingleNodeObjectData"
      },
      "UsedResources": [
        "Default/Button_Disable.png",
        "StartScene/NewButton.png"
      ],
      "ctype": "GameProjectData"
    }
  },
  "Type": "Scene"
}